b4/__init__.py
b4/command.py
b4/diff.py
b4/ez.py
b4/kr.py
b4/mbox.py
b4/pr.py
b4/ty.py
b4/man/b4.5.rst
b4/templates/shazam-merge-template.example
b4/templates/thanks-am-template.example
b4/templates/thanks-pr-template.example
b4-0.14.3.dist-info/licenses/COPYING
b4-0.14.3.dist-info/METADATA
b4-0.14.3.dist-info/WHEEL
b4-0.14.3.dist-info/entry_points.txt
b4-0.14.3.dist-info/top_level.txt
b4-0.14.3.dist-info/RECORD
