Metadata-Version: 2.4
Name: b4
Version: 0.14.3
Summary: A tool to work with public-inbox and patch archives
Author-email: Konstantin Ryabitsev <konstantin@linuxfoundation.org>
License:                     GNU GENERAL PUBLIC LICENSE
Project-URL: Homepage, https://git.kernel.org/pub/scm/utils/b4/b4.git/
Project-URL: Repository, https://git.kernel.org/pub/scm/utils/b4/b4.git
Project-URL: Documentation, https://b4.docs.kernel.org/
Keywords: git,public-inbox,lore.kernel.org,patch,email,workflow
Classifier: Environment :: Console
Classifier: Operating System :: POSIX :: Linux
Classifier: Intended Audience :: Developers
Classifier: License :: OSI Approved :: GNU General Public License v2 or later (GPLv2+)
Classifier: Topic :: Communications :: Email
Classifier: Topic :: Software Development
Classifier: Topic :: Utilities
Requires-Python: >=3.8
License-File: COPYING
Requires-Dist: requests<3.0,>=2.24
Requires-Dist: git-filter-repo<3.0,>=2.30
Requires-Dist: dkimpy<2.0,>=1.0
Requires-Dist: patatt<2.0,>=0.6
Dynamic: license-file
